deserialize/__init__.py
deserialize/conversions.py
deserialize/custom_deserializable.py
deserialize/decorators/__init__.py
deserialize/decorators/constructed.py
deserialize/decorators/default.py
deserialize/decorators/downcasting.py
deserialize/decorators/ignore.py
deserialize/decorators/key.py
deserialize/decorators/parser.py
deserialize/decorators/snake.py
deserialize/decorators/unhandled.py
deserialize/exceptions.py
deserialize/field.py
deserialize/metadata_cache.py
deserialize/py.typed
deserialize/raw_storage_mode.py
deserialize/type_checks.py
deserialize-2.2.0.dist-info/LICENSE
deserialize-2.2.0.dist-info/METADATA
deserialize-2.2.0.dist-info/WHEEL
deserialize-2.2.0.dist-info/RECORD
