Metadata-Version: 2.1
Name: deserialize
Version: 2.2.0
Summary: A library to make deserialization easy.
Home-page: https://github.com/dalemyers/deserialize
License: MIT
Keywords: deserialization,deserialize,objects,object,json
Author: Dale Myers
Author-email: dale@myers.io
Requires-Python: >=3.10,<4.0
Classifier: Development Status :: 5 - Production/Stable
Classifier: Intended Audience :: Developers
Classifier: License :: OSI Approved :: MIT License
Classifier: Programming Language :: Python :: 3
Classifier: Programming Language :: Python :: 3.10
Classifier: Programming Language :: Python :: 3.11
Classifier: Programming Language :: Python :: 3.12
Classifier: Programming Language :: Python :: 3.13
Classifier: Topic :: Software Development :: Libraries
Project-URL: Repository, https://github.com/dalemyers/deserialize
